{
    "status": "success",
    "message": "success",
    "data": {
        "pagination": {
            "total": 4,
            "uri": "?",
            "currentPage": 1,
            "next": null,
            "previous": null,
            "first": 1,
            "last": 1,
            "pages": 1
        },
        "records": [
            {
                "id": 137,
                "title": "\u6d4b\u8bd5\u6846\u67b6Mocha\u4f7f\u7528",
                "is_origin": "yes",
                "visited": 0,
                "commented": 0,
                "liked": 0,
                "updated_at": "1615783476",
                "user_id": 2,
                "is_draft": "no"
            },
            {
                "id": 136,
                "title": "Webpack\u4ece\u5165\u95e8\u5230\u53d1\u5e03\u4e00\u4e2aNPM\u5305(\u4e00)",
                "is_origin": "yes",
                "visited": 0,
                "commented": 0,
                "liked": 0,
                "updated_at": "1615198588",
                "user_id": 2,
                "is_draft": "no"
            },
            {
                "id": 99,
                "title": "\u8d2a\u5a6a\u7b97\u6cd5-\u56de\u6eaf",
                "is_origin": "yes",
                "visited": 2,
                "commented": 0,
                "liked": 0,
                "updated_at": "1615115743",
                "user_id": 2,
                "is_draft": "no"
            },
            {
                "id": 100,
                "title": "\u521d\u8bc6Laravel Facades\u548cContract",
                "is_origin": "yes",
                "visited": 0,
                "commented": 0,
                "liked": 0,
                "updated_at": "1614766374",
                "user_id": 2,
                "is_draft": "no"
            }
        ],
        "topics": [
            {
                "id": 0,
                "name": "\u6240\u6709\u4e13\u9898"
            },
            {
                "id": 17,
                "name": "ES7",
                "user_id": 2
            },
            {
                "id": 21,
                "name": "\u6570\u636e\u7ed3\u6784\u4e0e\u7b97\u6cd5",
                "user_id": 2
            }
        ],
        "currentTopicId": 0,
        "count": {
            "total": 4,
            "draft": 0,
            "deleted": 0
        }
    }
}